fort/__init__.py
fort/postgres.py
fort/sqlite.py
fort-2025.1.dist-info/WHEEL
fort-2025.1.dist-info/METADATA
fort-2025.1.dist-info/RECORD
