Metadata-Version: 2.4
Name: fort
Version: 2025.1
Summary: The Python database micropackage
Author: William Jackson
Author-email: William Jackson <william@subtlecoolness.com>
License-Expression: MIT
Classifier: Programming Language :: Python :: 3
Classifier: Operating System :: OS Independent
Requires-Python: >=3.9
Project-URL: Homepage, https://github.com/williamjacksn/fort
Project-URL: Issues, https://github.com/williamjacksn/fort/issues
